massmarket_hash_event/__init__.py
massmarket_hash_event/authentication_pb2.py
massmarket_hash_event/authentication_pb2.pyi
massmarket_hash_event/base_types_pb2.py
massmarket_hash_event/base_types_pb2.pyi
massmarket_hash_event/envelope_pb2.py
massmarket_hash_event/envelope_pb2.pyi
massmarket_hash_event/error_pb2.py
massmarket_hash_event/error_pb2.pyi
massmarket_hash_event/shop_events_pb2.py
massmarket_hash_event/shop_events_pb2.pyi
massmarket_hash_event/shop_requests_pb2.py
massmarket_hash_event/shop_requests_pb2.pyi
massmarket_hash_event/storage_pb2.py
massmarket_hash_event/storage_pb2.pyi
massmarket_hash_event/subscription_pb2.py
massmarket_hash_event/subscription_pb2.pyi
massmarket_hash_event/transport_pb2.py
massmarket_hash_event/transport_pb2.pyi
massmarket_hash_event-3.0.dist-info/METADATA
massmarket_hash_event-3.0.dist-info/WHEEL
massmarket_hash_event-3.0.dist-info/top_level.txt
massmarket_hash_event-3.0.dist-info/RECORD
